image2image_reg/__init__.py
image2image_reg/__main__.py
image2image_reg/_typing.py
image2image_reg/_version.py
image2image_reg/enums.py
image2image_reg/py.typed
image2image_reg/wrapper.py
image2image_reg/cli/__init__.py
image2image_reg/cli/_common.py
image2image_reg/cli/elastix.py
image2image_reg/cli/merge.py
image2image_reg/cli/simple_valis.py
image2image_reg/cli/valis.py
image2image_reg/elastix/__init__.py
image2image_reg/elastix/convert.py
image2image_reg/elastix/figures.py
image2image_reg/elastix/registration.py
image2image_reg/elastix/registration_map.py
image2image_reg/elastix/registration_utils.py
image2image_reg/elastix/transform.py
image2image_reg/elastix/transform_sequence.py
image2image_reg/elastix/transform_utils.py
image2image_reg/elastix/transformation_map.py
image2image_reg/elastix/visuals.py
image2image_reg/elastix/wsireg.py
image2image_reg/models/__init__.py
image2image_reg/models/bbox.py
image2image_reg/models/export.py
image2image_reg/models/modality.py
image2image_reg/models/preprocessing.py
image2image_reg/preprocessing/__init__.py
image2image_reg/preprocessing/convert.py
image2image_reg/preprocessing/mixin.py
image2image_reg/preprocessing/step.py
image2image_reg/preprocessing/utilities.py
image2image_reg/preprocessing/workflow.py
image2image_reg/utils/__init__.py
image2image_reg/utils/_test.py
image2image_reg/utils/affine.py
image2image_reg/utils/preprocessing.py
image2image_reg/utils/transform_utils.py
image2image_reg/utils/utilities.py
image2image_reg/utils/visuals.py
image2image_reg/valis/__init__.py
image2image_reg/valis/detect.py
image2image_reg/valis/matcher.py
image2image_reg/valis/preprocessing.py
image2image_reg/valis/slide_io.py
image2image_reg/valis/transform.py
image2image_reg/valis/utilities.py
image2image_reg/workflows/__init__.py
image2image_reg/workflows/_base.py
image2image_reg/workflows/elastix.py
image2image_reg/workflows/merge.py
image2image_reg/workflows/transform.py
image2image_reg/workflows/valis.py
image2image_reg-0.1.10.dist-info/licenses/LICENSE
image2image_reg-0.1.10.dist-info/METADATA
image2image_reg-0.1.10.dist-info/WHEEL
image2image_reg-0.1.10.dist-info/entry_points.txt
image2image_reg-0.1.10.dist-info/top_level.txt
image2image_reg-0.1.10.dist-info/RECORD
