Metadata-Version: 2.4
Name: image2image-reg
Version: 0.1.10
Summary: Whole slide image registration using elastix.
Author-email: "Lukasz G. Migas" <lukas.migas@yahoo.com>
License: BSD 3-Clause License
Project-URL: homepage, https://github.com/vandeplaslab/image2image-reg
Project-URL: repository, https://github.com/vandeplaslab/image2image-reg
Classifier: Development Status :: 3 - Alpha
Classifier: License :: OSI Approved :: BSD License
Classifier: Natural Language :: English
Classifier: Programming Language :: Python :: 3
Classifier: Programming Language :: Python :: 3.8
Classifier: Programming Language :: Python :: 3.9
Classifier: Programming Language :: Python :: 3.10
Classifier: Typing :: Typed
Requires-Python: >=3.8
License-File: LICENSE
Requires-Dist: pydantic>=2
Requires-Dist: numpy
Requires-Dist: itk-elastix
Requires-Dist: opencv-python
Requires-Dist: SimpleITK
Requires-Dist: scikit-image
Requires-Dist: click-groups
Requires-Dist: mpire
Requires-Dist: colour-science>=0.4.1
Requires-Dist: tabulate
Requires-Dist: loguru
Requires-Dist: image2image-io
Provides-Extra: valis
Requires-Dist: valis-wsi; extra == "valis"
Requires-Dist: opencv-contrib-python; extra == "valis"
Requires-Dist: fastcluster; extra == "valis"
Requires-Dist: scikit-learn; extra == "valis"
Provides-Extra: test
Requires-Dist: pytest>=6.0; extra == "test"
Requires-Dist: pytest-cov; extra == "test"
Provides-Extra: dev
Requires-Dist: black; extra == "dev"
Requires-Dist: ipython; extra == "dev"
Requires-Dist: mypy; extra == "dev"
Requires-Dist: pdbpp; extra == "dev"
Requires-Dist: pre-commit; extra == "dev"
Requires-Dist: rich; extra == "dev"
Requires-Dist: ruff; extra == "dev"
Requires-Dist: image2image-reg[test]; extra == "dev"
Dynamic: license-file
